{
  "formatVersion": 1,
  "database": {
    "version": 6,
    "identityHash": "ad71a771eb5093bb54fe7f0fa3ff77a2",
    "entities": [
      {
        "tableName": "MusicNotes",
        "createSql": "CREATE TABLE IF NOT EXISTS `${TABLE_NAME}` (`id` INTEGER NOT NULL, `latinName` TEXT NOT NULL, `englishName` TEXT NOT NULL, `latinNotation` TEXT NOT NULL, `englishNotation` TEXT NOT NULL, `octave` INTEGER NOT NULL, `maxHz` REAL NOT NULL, `minHz` REAL NOT NULL, `sharpIndicator` TEXT, `alternativeName` TEXT, PRIMARY KEY(`id`))",
        "fields": [
          {
            "fieldPath": "id",
            "columnName": "id",
            "affinity": "INTEGER",
            "notNull": true
          },
          {
            "fieldPath": "latinName",
            "columnName": "latinName",
            "affinity": "TEXT",
            "notNull": true
          },
          {
            "fieldPath": "englishName",
            "columnName": "englishName",
            "affinity": "TEXT",
            "notNull": true
          },
          {
            "fieldPath": "latinNotation",
            "columnName": "latinNotation",
            "affinity": "TEXT",
            "notNull": true
          },
          {
            "fieldPath": "englishNotation",
            "columnName": "englishNotation",
            "affinity": "TEXT",
            "notNull": true
          },
          {
            "fieldPath": "octave",
            "columnName": "octave",
            "affinity": "INTEGER",
            "notNull": true
          },
          {
            "fieldPath": "maxHz",
            "columnName": "maxHz",
            "affinity": "REAL",
            "notNull": true
          },
          {
            "fieldPath": "minHz",
            "columnName": "minHz",
            "affinity": "REAL",
            "notNull": true
          },
          {
            "fieldPath": "sharpIndicator",
            "columnName": "sharpIndicator",
            "affinity": "TEXT",
            "notNull": false
          },
          {
            "fieldPath": "alternativeName",
            "columnName": "alternativeName",
            "affinity": "TEXT",
            "notNull": false
          }
        ],
        "primaryKey": {
          "autoGenerate": false,
          "columnNames": [
            "id"
          ]
        },
        "indices": [],
        "foreignKeys": []
      },
      {
        "tableName": "Tunings",
        "createSql": "CREATE TABLE IF NOT EXISTS `${TABLE_NAME}` (`id` INTEGER PRIMARY KEY AUTOINCREMENT NOT NULL, `name` TEXT NOT NULL, `favourite` INTEGER NOT NULL)",
        "fields": [
          {
            "fieldPath": "id",
            "columnName": "id",
            "affinity": "INTEGER",
            "notNull": true
          },
          {
            "fieldPath": "name",
            "columnName": "name",
            "affinity": "TEXT",
            "notNull": true
          },
          {
            "fieldPath": "favourite",
            "columnName": "favourite",
            "affinity": "INTEGER",
            "notNull": true
          }
        ],
        "primaryKey": {
          "autoGenerate": true,
          "columnNames": [
            "id"
          ]
        },
        "indices": [],
        "foreignKeys": []
      },
      {
        "tableName": "TuningMusicNote",
        "createSql": "CREATE TABLE IF NOT EXISTS `${TABLE_NAME}` (`id` INTEGER PRIMARY KEY AUTOINCREMENT NOT NULL, `tuningId` INTEGER NOT NULL, `noteId` INTEGER NOT NULL, FOREIGN KEY(`tuningId`) REFERENCES `Tunings`(`id`) ON UPDATE NO ACTION ON DELETE NO ACTION , FOREIGN KEY(`noteId`) REFERENCES `MusicNotes`(`id`) ON UPDATE NO ACTION ON DELETE NO ACTION )",
        "fields": [
          {
            "fieldPath": "id",
            "columnName": "id",
            "affinity": "INTEGER",
            "notNull": true
          },
          {
            "fieldPath": "tuningId",
            "columnName": "tuningId",
            "affinity": "INTEGER",
            "notNull": true
          },
          {
            "fieldPath": "noteId",
            "columnName": "noteId",
            "affinity": "INTEGER",
            "notNull": true
          }
        ],
        "primaryKey": {
          "autoGenerate": true,
          "columnNames": [
            "id"
          ]
        },
        "indices": [],
        "foreignKeys": [
          {
            "table": "Tunings",
            "onDelete": "NO ACTION",
            "onUpdate": "NO ACTION",
            "columns": [
              "tuningId"
            ],
            "referencedColumns": [
              "id"
            ]
          },
          {
            "table": "MusicNotes",
            "onDelete": "NO ACTION",
            "onUpdate": "NO ACTION",
            "columns": [
              "noteId"
            ],
            "referencedColumns": [
              "id"
            ]
          }
        ]
      },
      {
        "tableName": "Songs",
        "createSql": "CREATE TABLE IF NOT EXISTS `${TABLE_NAME}` (`id` INTEGER PRIMARY KEY AUTOINCREMENT NOT NULL, `name` TEXT NOT NULL, `bandName` TEXT NOT NULL, `tuningId` INTEGER NOT NULL, `bpm` TEXT NOT NULL, `key` TEXT NOT NULL, FOREIGN KEY(`tuningId`) REFERENCES `Tunings`(`id`) ON UPDATE NO ACTION ON DELETE CASCADE )",
        "fields": [
          {
            "fieldPath": "id",
            "columnName": "id",
            "affinity": "INTEGER",
            "notNull": true
          },
          {
            "fieldPath": "name",
            "columnName": "name",
            "affinity": "TEXT",
            "notNull": true
          },
          {
            "fieldPath": "bandName",
            "columnName": "bandName",
            "affinity": "TEXT",
            "notNull": true
          },
          {
            "fieldPath": "tuningId",
            "columnName": "tuningId",
            "affinity": "INTEGER",
            "notNull": true
          },
          {
            "fieldPath": "bpm",
            "columnName": "bpm",
            "affinity": "TEXT",
            "notNull": true
          },
          {
            "fieldPath": "key",
            "columnName": "key",
            "affinity": "TEXT",
            "notNull": true
          }
        ],
        "primaryKey": {
          "autoGenerate": true,
          "columnNames": [
            "id"
          ]
        },
        "indices": [],
        "foreignKeys": [
          {
            "table": "Tunings",
            "onDelete": "CASCADE",
            "onUpdate": "NO ACTION",
            "columns": [
              "tuningId"
            ],
            "referencedColumns": [
              "id"
            ]
          }
        ]
      }
    ],
    "views": [],
    "setupQueries": [
      "CREATE TABLE IF NOT EXISTS room_master_table (id INTEGER PRIMARY KEY,identity_hash TEXT)",
      "INSERT OR REPLACE INTO room_master_table (id,identity_hash) VALUES(42, 'ad71a771eb5093bb54fe7f0fa3ff77a2')"
    ]
  }
}